electrasmart/__init__.py
electrasmart/py.typed
electrasmart/api/__init__.py
electrasmart/api/const.py
electrasmart/api/utils.py
electrasmart/device/__init__.py
electrasmart/device/const.py
pyElectra-1.2.3.dist-info/METADATA
pyElectra-1.2.3.dist-info/WHEEL
pyElectra-1.2.3.dist-info/top_level.txt
pyElectra-1.2.3.dist-info/RECORD
