Metadata-Version: 2.1
Name: pyElectra
Version: 1.2.3
Summary: Electra Smart Python Integration.
Author-email: Jafar Atili <at.jafar@outlook.com>
Project-URL: homepage, https://pypi.org/project/pyelectra/
Project-URL: repository, https://github.com/jafar-atili/pyelectra/
Keywords: home,automation,Electra,smart,Electra Smart,Air Condition
Classifier: Intended Audience :: Developers
Classifier: Operating System :: OS Independent
Classifier: Topic :: Home Automation
Classifier: Topic :: Software Development :: Libraries :: Python Modules
Classifier: Typing :: Typed
Requires-Python: >=3.9
Requires-Dist: aiohttp
